s2ism/__init__.py
s2ism/mag_finder.py
s2ism/misalignment.py
s2ism/psf_estimator.py
s2ism/s2ism.py
s2ism/shift_vectors_minimizer.py
s2ism-0.2.0.dist-info/licenses/LICENSE
s2ism-0.2.0.dist-info/METADATA
s2ism-0.2.0.dist-info/WHEEL
s2ism-0.2.0.dist-info/top_level.txt
s2ism-0.2.0.dist-info/RECORD
