Metadata-Version: 2.4
Name: s2ism
Version: 0.2.0
Summary: Reconstruction algorithm for enhanced resolution and optical sectioning in image scanning microscopy.
Home-page: https://github.com/VicidominiLab/s2ism
Author: Alessandro Zunino, Giacomo Garrè
Author-email: "Alessandro Zunino,Giacomo Garrè" <alessandro.zunino@iit.it>
Project-URL: Homepage, https://github.com/VicidominiLab/s2ism
Project-URL: Documentation, https://github.com/VicidominiLab/s2ISM/tree/main/examples
Classifier: Programming Language :: Python :: 3.7
Classifier: Programming Language :: Python :: 3.8
Classifier: Programming Language :: Python :: 3.9
Classifier: Programming Language :: Python :: 3.10
Classifier: Operating System :: OS Independent
Classifier: License :: OSI Approved :: GNU General Public License v3 or later (GPLv3+)
Requires-Python: >=3.7
License-File: LICENSE
Requires-Dist: numpy
Requires-Dist: matplotlib
Requires-Dist: scipy
Requires-Dist: scikit-image
Requires-Dist: brighteyes-ism
Requires-Dist: torch
Requires-Dist: tqdm
Provides-Extra: testing
Requires-Dist: tox; extra == "testing"
Requires-Dist: pytest; extra == "testing"
Requires-Dist: pytest-cov; extra == "testing"
Requires-Dist: pytest-qt; extra == "testing"
Requires-Dist: napari; extra == "testing"
Requires-Dist: pyqt5; extra == "testing"
Dynamic: license-file
